LICENSE_enumitem
README
defsetup.py
setup.cfg
setup.py
lib/stsci/__init__.py
lib/stsci.sphinxext.egg-info/PKG-INFO
lib/stsci.sphinxext.egg-info/SOURCES.txt
lib/stsci.sphinxext.egg-info/dependency_links.txt
lib/stsci.sphinxext.egg-info/namespace_packages.txt
lib/stsci.sphinxext.egg-info/not-zip-safe
lib/stsci.sphinxext.egg-info/top_level.txt
lib/stsci/sphinxext/__init__.py
lib/stsci/sphinxext/abstract.py
lib/stsci/sphinxext/conf.py
lib/stsci/sphinxext/narrow_field_lists.py
lib/stsci/sphinxext/parameter_anchor.py
lib/stsci/sphinxext/version.py
lib/stsci/sphinxext/latex/enumitem.sty
lib/stsci/sphinxext/latex/sphinxtsr.cls
lib/stsci/sphinxext/latex/stsci_logo.pdf
lib/stsci/sphinxext/stsci_sphinx_theme/theme.conf
lib/stsci/sphinxext/stsci_sphinx_theme/static/stsci_background.png
lib/stsci/sphinxext/stsci_sphinx_theme/static/stsci_logo.png
lib/stsci/sphinxext/stsci_sphinx_theme/static/stsci_sphinx.css_t