Metadata-Version: 1.1
Name: stsci.sphinxext
Version: 1.2.1
Summary: 
Home-page: http://www.stsci.edu/resources/software_hardware/stsci_python
Author: Michael Droettboom
Author-email: mdroe@stsci.edu
License: UNKNOWN
Platform: UNKNOWN
Classifier: Development Status :: 5 - Production/Stable
Classifier: Environment :: Plugins
Classifier: Intended Audience :: Developers
Classifier: Intended Audience :: Science/Research
Classifier: License :: OSI Approved :: BSD License
Classifier: Topic :: Software Development :: Documentation
